cc_sym.cpython-312-darwin.so
symengine/functions.py
symengine/CMakeLists.txt
symengine/__init__.py
symengine/sympy_compat.py
symengine/utilities.py
symengine/printing.py
symengine/tests/test_lambdify.py
symengine/tests/test_sage.py
symengine/tests/test_sympy_compat.py
symengine/tests/CMakeLists.txt
symengine/tests/test_solve.py
symengine/tests/test_subs.py
symengine/tests/__init__.py
symengine/tests/test_matrices.py
symengine/tests/test_series_expansion.py
symengine/tests/test_sympy_conv.py
symengine/tests/test_cse.py
symengine/tests/test_arit.py
symengine/tests/test_pickling.py
symengine/tests/test_printing.py
symengine/tests/test_functions.py
symengine/tests/test_dict_basic.py
symengine/tests/test_var.py
symengine/tests/test_expr.py
symengine/tests/test_number.py
symengine/tests/test_sympify.py
symengine/tests/test_ntheory.py
symengine/tests/test_sets.py
symengine/tests/test_symbol.py
symengine/tests/test_logic.py
symengine/tests/test_eval.py
symengine/lib/pywrapper.cpp
symengine/lib/symengine.pxd
symengine/lib/CMakeLists.txt
symengine/lib/symengine_wrapper.pyx
symengine/lib/py_callable_wrapper.h
symengine/lib/__init__.py
symengine/lib/config.pxi.in
symengine/lib/symengine_wrapper.cpython-312-darwin.so
symengine/lib/pywrapper.h
symengine/lib/symengine_wrapper.pxd
lcmtypes/__init__.py
lcmtypes/sym/_optimization_stats_t.py
lcmtypes/sym/_imu_integrated_measurement_delta_t.py
lcmtypes/sym/_linearization_offsets_t.py
lcmtypes/sym/_imu_integrated_measurement_t.py
lcmtypes/sym/_levenberg_marquardt_solver_failure_reason_t.py
lcmtypes/sym/_type_t.py
lcmtypes/sym/_key_t.py
lcmtypes/sym/__init__.py
lcmtypes/sym/_linearized_dense_factor_t.py
lcmtypes/sym/_lambda_update_type_t.py
lcmtypes/sym/_optimizer_params_t.py
lcmtypes/sym/_index_entry_t.py
lcmtypes/sym/_valuesf_t.py
lcmtypes/sym/_optimization_iteration_t.py
lcmtypes/sym/_linearization_sparse_factor_helper_t.py
lcmtypes/sym/_sparse_matrix_structure_t.py
symforce-0.10.1.dist-info/RECORD
symforce-0.10.1.dist-info/WHEEL
symforce-0.10.1.dist-info/top_level.txt
symforce-0.10.1.dist-info/METADATA
symforce-0.10.1.dist-info/licenses/LICENSE
