Metadata-Version: 2.1
Name: symforce
Version: 0.10.1
Summary: Fast symbolic computation, code generation, and nonlinear optimization for robotics
Home-page: https://symforce.org
Author-email: "Skydio, Inc." <hayk@skydio.com>
License: Apache 2.0
Project-URL: Bug Tracker, https://github.com/symforce-org/symforce/issues
Project-URL: Source, https://github.com/symforce-org/symforce
Keywords: python,computer-vision,cpp,robotics,optimization,structure-from-motion,motion-planning,code-generation,slam,autonomous-vehicles,symbolic-computation
Classifier: Development Status :: 4 - Beta
Classifier: Intended Audience :: Developers
Classifier: Intended Audience :: Education
Classifier: Intended Audience :: Science/Research
Classifier: Topic :: Scientific/Engineering :: Artificial Intelligence
Classifier: Topic :: Scientific/Engineering :: Mathematics
Classifier: Topic :: Software Development :: Code Generators
Classifier: Topic :: Software Development :: Embedded Systems
Classifier: Topic :: Software Development :: Libraries :: Python Modules
Classifier: Topic :: Education :: Computer Aided Instruction (CAI)
Classifier: Programming Language :: Python
Classifier: Programming Language :: Python :: 3.8
Classifier: Programming Language :: Python :: 3.9
Classifier: Programming Language :: Python :: 3.10
Classifier: Programming Language :: Python :: 3.11
Classifier: Programming Language :: Python :: 3.12
Classifier: Programming Language :: Python :: 3 :: Only
Classifier: Programming Language :: C++
Classifier: License :: OSI Approved :: Apache Software License
Classifier: Operating System :: OS Independent
Requires-Python: >=3.8
License-File: LICENSE
Requires-Dist: ruff
Requires-Dist: clang-format
Requires-Dist: graphviz
Requires-Dist: jinja2
Requires-Dist: numpy<2.0
Requires-Dist: scipy
Requires-Dist: skymarshal==0.10.1
Requires-Dist: sympy~=1.11.1
Requires-Dist: symforce-sym==0.10.1
Requires-Dist: typing-extensions; python_version < "3.9"
Provides-Extra: dev
Requires-Dist: furo; extra == "dev"
Requires-Dist: ipykernel; extra == "dev"
Requires-Dist: ipython-genutils; extra == "dev"
Requires-Dist: matplotlib; extra == "dev"
Requires-Dist: myst-parser; extra == "dev"
Requires-Dist: nbsphinx; extra == "dev"
Requires-Dist: nbstripout; extra == "dev"
Requires-Dist: pandas; extra == "dev"
Requires-Dist: plotly; extra == "dev"
Requires-Dist: Sphinx; extra == "dev"
Requires-Dist: sphinx-copybutton; extra == "dev"
Requires-Dist: sphinxext-opengraph; extra == "dev"
Requires-Dist: breathe; extra == "dev"
Requires-Dist: argh; extra == "dev"
Requires-Dist: coverage; extra == "dev"
Requires-Dist: jinja2~=3.0; extra == "dev"
Requires-Dist: mypy~=1.11.0; extra == "dev"
Requires-Dist: numba; extra == "dev"
Requires-Dist: pybind11-stubgen>=2.5.3; extra == "dev"
Requires-Dist: ruff~=0.9.7; extra == "dev"
Requires-Dist: types-jinja2; extra == "dev"
Requires-Dist: types-requests; extra == "dev"
Requires-Dist: types-setuptools; extra == "dev"
Requires-Dist: uv>=0.2.0; extra == "dev"
Provides-Extra: docs
Requires-Dist: furo; extra == "docs"
Requires-Dist: ipykernel; extra == "docs"
Requires-Dist: ipython-genutils; extra == "docs"
Requires-Dist: matplotlib; extra == "docs"
Requires-Dist: myst-parser; extra == "docs"
Requires-Dist: nbsphinx; extra == "docs"
Requires-Dist: nbstripout; extra == "docs"
Requires-Dist: pandas; extra == "docs"
Requires-Dist: plotly; extra == "docs"
Requires-Dist: Sphinx; extra == "docs"
Requires-Dist: sphinx-copybutton; extra == "docs"
Requires-Dist: sphinxext-opengraph; extra == "docs"
Requires-Dist: breathe; extra == "docs"
Provides-Extra: setup
Requires-Dist: setuptools>=62.3.0; extra == "setup"
Requires-Dist: setuptools-scm>=8; extra == "setup"
Requires-Dist: wheel; extra == "setup"
Requires-Dist: pip; extra == "setup"
Requires-Dist: cmake<3.27,>=3.17; extra == "setup"
Requires-Dist: cython<3,>=0.19.1; extra == "setup"
Requires-Dist: skymarshal==0.10.1; extra == "setup"
